hanako/__init__.py
hanako/meta.py
hanako/cli/__init__.py
hanako/cli/__main__.py
hanako/cli/server.py
hanako/command/__init__.py
hanako/command/api.py
hanako/model/__init__.py
hanako/model/player.py
hanako/model/player_repo.py
hanako/model/world.py
hanako/server/__init__.py
hanako/server/api.py
hanako/server/player_api.py
hanako/server/room_api.py
hanako-0.0.1.dist-info/LICENSE
hanako-0.0.1.dist-info/METADATA
hanako-0.0.1.dist-info/WHEEL
hanako-0.0.1.dist-info/top_level.txt
hanako-0.0.1.dist-info/RECORD
