Metadata-Version: 2.1
Name: hanako
Version: 0.0.1
Summary: Real time multiplayer game server.
Home-page: https://github.com/BitolaHacklab/Hanako
Author: BitolaHacklab
Author-email: dev@bitolahacklab.org
License: UNKNOWN
Platform: UNKNOWN
Classifier: Programming Language :: Python :: 3
Classifier: Development Status :: 3 - Alpha
Classifier: Intended Audience :: Developers
Classifier: Intended Audience :: Other Audience
Classifier: License :: OSI Approved :: Apache Software License
Classifier: Topic :: Games/Entertainment
Classifier: Topic :: Software Development :: Libraries
